oaib/Auto.py
oaib/Batch.py
oaib/__init__.py
oaib/config.py
oaib/utils.py
oaib-1.2.0.dist-info/LICENSE
oaib-1.2.0.dist-info/METADATA
oaib-1.2.0.dist-info/WHEEL
oaib-1.2.0.dist-info/top_level.txt
oaib-1.2.0.dist-info/RECORD
