Metadata-Version: 2.1
Name: oaib
Version: 1.2.0
Summary: A Python library for making rate-limited, async batch requests to the OpenAI API.
Author-email: CTJ Lewis <lewis@spellcraft.org>
License: MIT
Classifier: Programming Language :: Python :: 3
Classifier: License :: OSI Approved :: MIT License
Classifier: Operating System :: OS Independent
Requires-Python: >=3.9
License-File: LICENSE
Requires-Dist: pandas >=1.5.3
Requires-Dist: tqdm >=4.66.1
Requires-Dist: openai >=1.11.0
